fideslang/__init__.py
fideslang/_version.py
fideslang/default_fixtures.py
fideslang/manifests.py
fideslang/models.py
fideslang/parse.py
fideslang/py.typed
fideslang/relationships.py
fideslang/utils.py
fideslang/validation.py
fideslang/default_taxonomy/__init__.py
fideslang/default_taxonomy/data_categories.py
fideslang/default_taxonomy/data_subjects.py
fideslang/default_taxonomy/data_uses.py
fideslang/default_taxonomy/organizations.py
fideslang/default_taxonomy/utils.py
fideslang/gvl/__init__.py
fideslang/gvl/gvl_data_category_mapping.json
fideslang/gvl/gvl_data_use_mapping.json
fideslang/gvl/gvl_feature_mapping.json
fideslang/gvl/models.py
fideslang-3.1.2.dist-info/licenses/LICENSE
fideslang-3.1.2.dist-info/METADATA
fideslang-3.1.2.dist-info/WHEEL
fideslang-3.1.2.dist-info/top_level.txt
fideslang-3.1.2.dist-info/RECORD
