Metadata-Version: 2.4
Name: fideslang
Version: 3.1.2
Summary: Fides Taxonomy Language
Author-email: "Ethyca, Inc." <fidesteam@ethyca.com>
License-Expression: Apache-2.0
Project-URL: documentation, https://github.com/ethyca/fideslang
Project-URL: changelog, https://github.com/ethyca/fideslang/blob/main/CHANGELOG.md
Classifier: Programming Language :: Python :: 3 :: Only
Classifier: Programming Language :: Python :: 3.9
Classifier: Programming Language :: Python :: 3.10
Classifier: Programming Language :: Python :: 3.11
Classifier: Topic :: Software Development :: Libraries
Requires-Python: <4,>=3.9
License-File: LICENSE
Requires-Dist: pydantic<=2.7.1,>=2.3.0
Requires-Dist: pyyaml<7,>=5
Requires-Dist: packaging>=20.0
Dynamic: license-file
